README.md
README.rst
setup.py
pyprf_feature/__init__.py
pyprf_feature.egg-info/PKG-INFO
pyprf_feature.egg-info/SOURCES.txt
pyprf_feature.egg-info/dependency_links.txt
pyprf_feature.egg-info/entry_points.txt
pyprf_feature.egg-info/requires.txt
pyprf_feature.egg-info/top_level.txt
pyprf_feature/analysis/__init__.py
pyprf_feature/analysis/__main__.py
pyprf_feature/analysis/find_prf_cpu.py
pyprf_feature/analysis/find_prf_gpu.py
pyprf_feature/analysis/find_prf_utils_np.py
pyprf_feature/analysis/load_config.py
pyprf_feature/analysis/model_creation_main.py
pyprf_feature/analysis/model_creation_opt.py
pyprf_feature/analysis/model_creation_utils.py
pyprf_feature/analysis/prepare.py
pyprf_feature/analysis/pyprf_main.py
pyprf_feature/analysis/pyprf_opt_brute.py
pyprf_feature/analysis/pyprf_opt_ep.py
pyprf_feature/analysis/pyprf_sim.py
pyprf_feature/analysis/pyprf_sim_ep.py
pyprf_feature/analysis/save_fit_tc_nii.py
pyprf_feature/analysis/utils_general.py
pyprf_feature/analysis/utils_hrf.py