Metadata-Version: 1.0
Name: pyprf-feature
Version: 1.1.0
Summary: A free & open source package for finding best-fitting                     population receptive field (PRF) models and feature                     weights for fMRI data.
Home-page: https://github.com/MSchnei/pyprf_feature
Author: Marian Schneider, Ingo Marquardt
Author-email: marian.schneider@maastrichtuniversity.nl
License: GNU General Public License Version 3
Keywords: pRF,fMRI,retinotopy,feature weights
Platform: UNKNOWN
